_version.py
lazyfunc/__init__.py
lazyfunc/arguments.py
lazyfunc/lazy_func.py
lazyfunc/operators.py
lazyfunc/utils.py
lazyfunc-0.2.0.dist-info/LICENSE
lazyfunc-0.2.0.dist-info/METADATA
lazyfunc-0.2.0.dist-info/WHEEL
lazyfunc-0.2.0.dist-info/top_level.txt
lazyfunc-0.2.0.dist-info/RECORD
